setup.py
bin/monitoring-agent
monitoring_agent/__init__.py
monitoring_agent/linux_monitoring.py
monitoring_agent/monitoring_agent.py
monitoring_agent.egg-info/PKG-INFO
monitoring_agent.egg-info/SOURCES.txt
monitoring_agent.egg-info/dependency_links.txt
monitoring_agent.egg-info/requires.txt
monitoring_agent.egg-info/top_level.txt