Metadata-Version: 1.0
Name: monitoring-agent
Version: 0.1.2
Summary: Agent to collect system metrics for Linux machines
Home-page: https://github.com/adimania/monitoring_agent
Author: Aditya Patawari
Author-email: aditya@adityapatawari.com
License: GPLv3
Platform: UNKNOWN
